setup.cfg
setup.py
crowdrouter/__init__.py
crowdrouter/crowd_stats.py
crowdrouter/decorators.py
crowdrouter/errors.py
crowdrouter/utils.py
crowdrouter.egg-info/PKG-INFO
crowdrouter.egg-info/SOURCES.txt
crowdrouter.egg-info/dependency_links.txt
crowdrouter.egg-info/requires.txt
crowdrouter.egg-info/top_level.txt
crowdrouter/context/__init__.py
crowdrouter/context/abstract_request_strategy.py
crowdrouter/context/crowd_object.py
crowdrouter/context/crowdrequest.py
crowdrouter/context/crowdresponse.py
crowdrouter/context/django_request_strategy.py
crowdrouter/context/flask_request_strategy.py
crowdrouter/context/mock_request_strategy.py
crowdrouter/crowdrouter/__init__.py
crowdrouter/crowdrouter/abstract_crowdrouter.py
crowdrouter/task/__init__.py
crowdrouter/task/abstract_crowd_choice.py
crowdrouter/task/abstract_loop_condition_crowd_choice.py
crowdrouter/task/abstract_task.py
crowdrouter/workflow/__init__.py
crowdrouter/workflow/abstract_workflow.py
crowdrouter/workflow/crowd_pipeline.py