Metadata-Version: 1.1
Name: crowdrouter
Version: 1.5.4
Summary: A framework for architecting tasks to the crowd.
Home-page: https://github.com/Project-EPIC/crowdrouter
Author: Mario Barrenechea
Author-email: mbarrenecheajr@gmail.com
License: MIT
Download-URL: https://github.com/Project-EPIC/crowdrouter/archive/1.5.4.tar.gz
Keywords: crowdsourcing,tasks,workflows
Platform: UNKNOWN
